odoo/addons/l10n_fr_hr_check_ssnid/README.rst
odoo/addons/l10n_fr_hr_check_ssnid/__init__.py
odoo/addons/l10n_fr_hr_check_ssnid/__manifest__.py
odoo/addons/l10n_fr_hr_check_ssnid/i18n/fr.po
odoo/addons/l10n_fr_hr_check_ssnid/i18n/l10n_fr_hr_check_ssnid.pot
odoo/addons/l10n_fr_hr_check_ssnid/models/__init__.py
odoo/addons/l10n_fr_hr_check_ssnid/models/hr_employee.py
odoo/addons/l10n_fr_hr_check_ssnid/readme/CONTRIBUTORS.rst
odoo/addons/l10n_fr_hr_check_ssnid/readme/DESCRIPTION.rst
odoo/addons/l10n_fr_hr_check_ssnid/readme/INSTALL.rst
odoo/addons/l10n_fr_hr_check_ssnid/readme/USAGE.rst
odoo/addons/l10n_fr_hr_check_ssnid/static/description/icon.png
odoo/addons/l10n_fr_hr_check_ssnid/static/description/index.html
odoo/addons/l10n_fr_hr_check_ssnid/tests/__init__.py
odoo/addons/l10n_fr_hr_check_ssnid/tests/test_ssnid.py
odoo/addons/l10n_fr_hr_check_ssnid/views/hr_employee.xml
odoo14_addon_l10n_fr_hr_check_ssnid-14.0.1.0.1.dist-info/METADATA
odoo14_addon_l10n_fr_hr_check_ssnid-14.0.1.0.1.dist-info/WHEEL
odoo14_addon_l10n_fr_hr_check_ssnid-14.0.1.0.1.dist-info/top_level.txt
odoo14_addon_l10n_fr_hr_check_ssnid-14.0.1.0.1.dist-info/RECORD
