Metadata-Version: 2.1
Name: odoo14-addon-l10n-fr-hr-check-ssnid
Version: 14.0.1.0.1
Summary: Check validity of Social Security Numbers in French companies
Home-page: https://github.com/OCA/l10n-france
Author: Akretion,Odoo Community Association (OCA)
Author-email: support@odoo-community.org
License: AGPL-3
Platform: UNKNOWN
Classifier: Programming Language :: Python
Classifier: Framework :: Odoo
Classifier: License :: OSI Approved :: GNU Affero General Public License v3
Requires-Python: >=3.6
Requires-Dist: odoo (<14.1dev,>=14.0a)
Requires-Dist: python-stdnum
